django_iam_dbauth/__init__.py
django_iam_dbauth/utils.py
django_iam_dbauth/aws/__init__.py
django_iam_dbauth/aws/database_wrapper.py
django_iam_dbauth/aws/mysql/__init__.py
django_iam_dbauth/aws/mysql/base.py
django_iam_dbauth/aws/postgresql/__init__.py
django_iam_dbauth/aws/postgresql/base.py
django_iam_dbauth-0.2.1.dist-info/METADATA
django_iam_dbauth-0.2.1.dist-info/WHEEL
django_iam_dbauth-0.2.1.dist-info/licenses/LICENSE
django_iam_dbauth-0.2.1.dist-info/RECORD
