Metadata-Version: 2.3
Name: django-iam-dbauth
Version: 0.2.1
Summary: Django database backends to use AWS Database IAM Authentication
Project-URL: Homepage, https://github.com/LabD/django-iam-dbauth
Author-email: Lab Digital <opensource@labdigital.nl>
License: MIT
License-File: LICENSE
Classifier: Development Status :: 5 - Production/Stable
Classifier: Environment :: Web Environment
Classifier: Framework :: Django
Classifier: Framework :: Django :: 4.2
Classifier: Framework :: Django :: 5.0
Classifier: Framework :: Django :: 5.1
Classifier: License :: OSI Approved :: MIT License
Classifier: Programming Language :: Python
Classifier: Programming Language :: Python :: 3
Classifier: Programming Language :: Python :: 3.8
Classifier: Programming Language :: Python :: 3.9
Classifier: Programming Language :: Python :: 3.10
Classifier: Programming Language :: Python :: 3.11
Classifier: Programming Language :: Python :: 3.12
Requires-Dist: boto3
Requires-Dist: django>=4.2
Requires-Dist: dnspython
